<tfg>
    <fontoshir>
      <hir>
        <![CDATA[
          <h1>Könyveket és a verseket erre az Instagram fiókra lehet küldeni: ggergogg</h1>
        ]]>
      </hir>
      <hir>
        <![CDATA[
          <h1>Elérhető a könyvek, versek menü!</h1>
        ]]>
      </hir>
      <hir>
        <![CDATA[
              <h1 onclick="Swal.fire('', 'TFG Discord szerverre ezzel a linkkel tudtok csatlakozni.', 'info')">🔗TFG Discord: discord.gg/kSDG9mQs6R🔗</h1>
         ]]>
      </hir>
    </fontoshir>
    <beallitasok>
        <fohatter>
            <img>https://szerencsi-tokaji.cms.intezmeny.edir.hu/uploads/medium_2024_09_30_18_56_45_9262bf4ef1.png</img>
            <img>https://szerencsi-tokaji.cms.intezmeny.edir.hu/uploads/2024_09_30_18_57_46_23a74b5196.png</img>
            <img>https://szerencsi-tokaji.cms.intezmeny.edir.hu/uploads/medium_suli_legi3_a46b0e054d.png</img>
            <img>https://szerencsi-tokaji.cms.intezmeny.edir.hu/uploads/2024_09_30_19_08_07_06edefc395.png</img>
        </fohatter>
    </beallitasok>
    <menetrend>
        <![CDATA[
            <h2>Csengetési rend</h2>
            <ul>
                <li data-time="07:50-08:35">1. 07:50-08:35</li>
                <li data-time="08:40-09:25">2. 08:40-09:25</li>
                <li data-time="09:35-10:20">3. 09:35-10:20</li>
                <li data-time="10:30-11:15">4. 10:30-11:15</li>
                <li data-time="11:25-12:10">5. 11:25-12:10</li>
                <li data-time="12:15-13:00">6. 12:15-13:00</li>
                <li data-time="13:05-13:50">7. 13:05-13:50</li>
                <li data-time="13:55-14:40">8. 13:55-14:40</li>
                <li data-time="14:45-15:30">9. 14:45-15:30</li>
            </ul>
        ]]>
    </menetrend>
</tfg>
